{
    "topic": "Future Perfect",
    "pages": [
      {
        "questions":  [
          {
            "type": "ImageDisplay",
            "imagePath": "B2/4FuturePerf/1.png"
          }
        ]
      },
      {
        "questions":  [
          {
            "type": "ImageDisplay",
            "imagePath": "B2/4FuturePerf/2.png"
          }
        ]
      },
      {
        "questions":  [
          {
            "type": "ImageDisplay",
            "imagePath": "B2/4FuturePerf/3.png"
          }
        ]
      },
      {
        "questions":  [
          {
            "type": "ImageDisplay",
            "imagePath": "B2/4FuturePerf/4.png"
          }
        ]
      }
    ]
  }
  